custom_viz_lib/__init__.py
custom_viz_lib/chart.py
custom_viz_lib/data_loader.py
custom_viz_lib/theme.py
custom_viz_lib/utils.py
tests/__init__.py
tests/test_chart.py
tests/test_data_loader.py
tests/test_theme.py
tests/test_utils.py
custom_viz_lib-1.0.1.dist-info/METADATA
custom_viz_lib-1.0.1.dist-info/WHEEL
custom_viz_lib-1.0.1.dist-info/top_level.txt
custom_viz_lib-1.0.1.dist-info/RECORD
