Metadata-Version: 2.1
Name: custom-viz-lib
Version: 1.0.1
Summary: A customizable data visualization library
Author: Aso Okada
Author-email: s2222083@stu.musashino-u.ac.jp
License: UNKNOWN
Platform: UNKNOWN
Classifier: Programming Language :: Python :: 3
Classifier: License :: OSI Approved :: MIT License
Classifier: Operating System :: OS Independent
Requires-Python: >=3.6
Requires-Dist: matplotlib
Requires-Dist: pandas
Requires-Dist: seaborn
